nscmd/__init__.py
nscmd-0.1.1.dist-info/LICENSE
nscmd-0.1.1.dist-info/METADATA
nscmd-0.1.1.dist-info/WHEEL
nscmd-0.1.1.dist-info/top_level.txt
nscmd-0.1.1.dist-info/RECORD
