Metadata-Version: 2.1
Name: nscmd
Version: 0.1.1
Summary: A terminal user interface (TUI) for GNU/Linux systems which implements namespaces.
Home-page: https://github.com/ropbear/nscmd
Author: ropbear
Author-email: pypi@selfhosted.systems
License: GPLv3
Project-URL: Bug Tracker, https://github.com/ropbear/nscmd/issues
Classifier: License :: OSI Approved :: GNU General Public License v3 (GPLv3)
Classifier: Programming Language :: Python :: 3
Classifier: Operating System :: OS Independent
Requires-Python: >=3.8
License-File: LICENSE
